collate_cs/__init__.py
collate_cs/__main__.py
collate_cs/add_close_braces.py
collate_cs/collate_cs.py
collate_cs/construct_pre_method_string.py
collate_cs/cs_file_count.py
collate_cs/finish_semicolons.py
collate_cs/get_new_indent.py
collate_cs/get_src.py
collate_cs/is_complete_line.py
collate_cs/join_lines.py
collate_cs/namespace_override.py
collate_cs/process_class_files.py
collate_cs/process_line.py
collate_cs/process_method.py
collate_cs/read_class_files.py
collate_cs/remove_extra_semicolons.py
collate_cs/replace_keywords.py
collate_cs/write_src.py
collate_cs-0.47.dist-info/DESCRIPTION.rst
collate_cs-0.47.dist-info/LICENSE.txt
collate_cs-0.47.dist-info/METADATA
collate_cs-0.47.dist-info/RECORD
collate_cs-0.47.dist-info/WHEEL
collate_cs-0.47.dist-info/entry_points.txt
collate_cs-0.47.dist-info/metadata.json
collate_cs-0.47.dist-info/top_level.txt
